distributions_v2024/Binomialdistribution.py
distributions_v2024/Gaussiandistribution.py
distributions_v2024/Generaldistribution.py
distributions_v2024/__init__.py
distributions_v2024-1.0.dist-info/DESCRIPTION.rst
distributions_v2024-1.0.dist-info/METADATA
distributions_v2024-1.0.dist-info/RECORD
distributions_v2024-1.0.dist-info/WHEEL
distributions_v2024-1.0.dist-info/metadata.json
distributions_v2024-1.0.dist-info/top_level.txt
