Metadata-Version: 2.0
Name: distributions-v2024
Version: 1.0
Summary: Probability distributions
Home-page: UNKNOWN
Author: UNKNOWN
Author-email: UNKNOWN
License: UNKNOWN
Platform: UNKNOWN
